gff_to_xlsx.py
gff_to_xlsx-0.1.dist-info/METADATA
gff_to_xlsx-0.1.dist-info/WHEEL
gff_to_xlsx-0.1.dist-info/entry_points.txt
gff_to_xlsx-0.1.dist-info/top_level.txt
gff_to_xlsx-0.1.dist-info/RECORD
