Metadata-Version: 2.1
Name: gff-to-xlsx
Version: 0.1
Summary: A tool to convert GFF files to Excel (XLSX) format.
Home-page: UNKNOWN
Author: Emmanuel Agyare
Author-email: your_email@example.com
License: UNKNOWN
Platform: UNKNOWN
Requires-Dist: pandas
Requires-Dist: openpyxl
